{
    "key": "group_5d17d7b1829b6",
    "title": "Header Style",
    "fields": [
        {
            "key": "field_5d17d7f1eb04a",
            "label": "Light or Dark?",
            "name": "light_or_dark_header",
            "type": "select",
            "instructions": "Select light for darkly colored backgrounds, and dark for lightly colored backgrounds",
            "required": 0,
            "conditional_logic": 0,
            "wrapper": {
                "width": "",
                "class": "",
                "id": ""
            },
            "choices": {
                "light": "Light Header",
                "dark": "Dark Header"
            },
            "default_value": [
                "dark"
            ],
            "allow_null": 0,
            "multiple": 0,
            "ui": 0,
            "return_format": "value",
            "ajax": 0,
            "placeholder": ""
        }
    ],
    "location": [
        [
            {
                "param": "post_type",
                "operator": "==",
                "value": "page"
            },
            {
                "param": "post_template",
                "operator": "!=",
                "value": "listings.php"
            }
        ],
        [
            {
                "param": "post_type",
                "operator": "==",
                "value": "torque_listing"
            }
        ]
    ],
    "menu_order": 0,
    "position": "normal",
    "style": "default",
    "label_placement": "top",
    "instruction_placement": "label",
    "hide_on_screen": "",
    "active": 1,
    "description": "",
    "modified": 1565647000
}